pyproject.toml
setup.py
netbox_vpn_inventory/__init__.py
netbox_vpn_inventory/filters.py
netbox_vpn_inventory/forms.py
netbox_vpn_inventory/jobs.py
netbox_vpn_inventory/models.py
netbox_vpn_inventory/plugin.py
netbox_vpn_inventory/tables.py
netbox_vpn_inventory/urls.py
netbox_vpn_inventory/views.py
netbox_vpn_inventory.egg-info/PKG-INFO
netbox_vpn_inventory.egg-info/SOURCES.txt
netbox_vpn_inventory.egg-info/dependency_links.txt
netbox_vpn_inventory.egg-info/not-zip-safe
netbox_vpn_inventory.egg-info/top_level.txt